docs/Makefile
docs/conf.py
docs/index.rst
docs/make.bat
docs/rtd-pip-requirements.txt
docs/_static/css/custom-tweakwcs.css
docs/exts/numfig.py
docs/source/CHANGELOG.rst
docs/source/LICENSE.rst
docs/source/correctors.rst
docs/source/imalign.rst
docs/source/linalg.rst
docs/source/linearfit.rst
docs/source/matchutils.rst
docs/source/wcsimage.rst
docs/source/wcsutils.rst
notebooks/align_fits_wcs.ipynb
tweakwcs/__init__.py
tweakwcs/_version.py
tweakwcs/correctors.py
tweakwcs/imalign.py
tweakwcs/linalg.py
tweakwcs/linearfit.py
tweakwcs/matchutils.py
tweakwcs/tpwcs.py
tweakwcs/wcsimage.py
tweakwcs/wcsutils.py
tweakwcs/tests/__init__.py
tweakwcs/tests/conftest.py
tweakwcs/tests/helper_correctors.py
tweakwcs/tests/test_correctors.py
tweakwcs/tests/test_imalign.py
tweakwcs/tests/test_jwst_utils.py
tweakwcs/tests/test_linalg.py
tweakwcs/tests/test_linearfit.py
tweakwcs/tests/test_matchutils.py
tweakwcs/tests/test_multichip_fitswcs.py
tweakwcs/tests/test_multichip_jwst.py
tweakwcs/tests/test_wcsimage.py
tweakwcs/tests/test_wcsutils.py
tweakwcs/tests/data/convex_hull_proximity.cat
tweakwcs/tests/data/ref.cat
tweakwcs/tests/data/sparse-2dhist.fits
tweakwcs/tests/data/wfc3_uvis1.cat
tweakwcs/tests/data/wfc3_uvis1.hdr
tweakwcs/tests/data/wfc3_uvis2.cat
tweakwcs/tests/data/wfc3_uvis2.hdr
tweakwcs/utils/__init__.py
tweakwcs/utils/jwst_utils.py
tweakwcs-0.8.12.dist-info/licenses/LICENSE.txt
tweakwcs-0.8.12.dist-info/METADATA
tweakwcs-0.8.12.dist-info/WHEEL
tweakwcs-0.8.12.dist-info/top_level.txt
tweakwcs-0.8.12.dist-info/RECORD
